Metadata-Version: 1.1
Name: infostore
Version: 1.0
Summary: Various types of data storage in python
Home-page: encry.cpnerd.koding.io/infostore.py
Author: CPNerd
Author-email: shadow889566@gmail.com
License: MIT
Platform: UNKNOWN
Classifier: Development Status :: 5 - Production/Stable
Classifier: License :: OSI Approved :: MIT License
Classifier: Programming Language :: Python :: 2.7
Classifier: Intended Audience :: Developers
